ncp_dataquery/__init__.py
ncp_dataquery/_version.py
ncp_dataquery/auth.py
ncp_dataquery/client.py
ncp_dataquery/constants.py
ncp_dataquery/dbapi.py
ncp_dataquery/exceptions.py
ncp_dataquery/logging.py
ncp_dataquery/mapper.py
ncp_dataquery/transaction.py
ncp_dataquery/types.py
ncp_dataquery/sqlalchemy/__init__.py
ncp_dataquery/sqlalchemy/compiler.py
ncp_dataquery/sqlalchemy/datatype.py
ncp_dataquery/sqlalchemy/dialect.py
ncp_dataquery/sqlalchemy/error.py
ncp_dataquery/sqlalchemy/util.py
ncp_dataquery-0.333.0.dist-info/licenses/LICENSE
ncp_dataquery-0.333.0.dist-info/METADATA
ncp_dataquery-0.333.0.dist-info/WHEEL
ncp_dataquery-0.333.0.dist-info/entry_points.txt
ncp_dataquery-0.333.0.dist-info/top_level.txt
ncp_dataquery-0.333.0.dist-info/RECORD
