Metadata-Version: 2.4
Name: ncp_dataquery
Version: 0.333.0
Summary: Client for the Trino distributed SQL Engine
Home-page: https://github.com/trinodb/trino-python-client
Author: Trino Team
Author-email: python-client@trino.io
License: Apache 2.0
Classifier: Development Status :: 4 - Beta
Classifier: Intended Audience :: Developers
Classifier: License :: OSI Approved :: Apache Software License
Classifier: Operating System :: MacOS :: MacOS X
Classifier: Operating System :: POSIX
Classifier: Operating System :: Microsoft :: Windows
Classifier: Programming Language :: Python
Classifier: Programming Language :: Python :: 3
Classifier: Programming Language :: Python :: 3.9
Classifier: Programming Language :: Python :: 3.10
Classifier: Programming Language :: Python :: 3.11
Classifier: Programming Language :: Python :: 3.12
Classifier: Programming Language :: Python :: 3.13
Classifier: Programming Language :: Python :: Implementation :: CPython
Classifier: Programming Language :: Python :: Implementation :: PyPy
Classifier: Topic :: Database :: Front-Ends
Requires-Python: >=3.9
License-File: LICENSE
Requires-Dist: lz4
Requires-Dist: python-dateutil
Requires-Dist: pytz
Requires-Dist: requests>=2.31.0
Requires-Dist: tzlocal
Requires-Dist: zstandard
Provides-Extra: all
Requires-Dist: requests_kerberos; extra == "all"
Requires-Dist: sqlalchemy>=1.3; extra == "all"
Provides-Extra: kerberos
Requires-Dist: requests_kerberos; extra == "kerberos"
Provides-Extra: gssapi
Requires-Dist: requests_gssapi; extra == "gssapi"
Requires-Dist: krb5==0.5.1; extra == "gssapi"
Provides-Extra: sqlalchemy
Requires-Dist: sqlalchemy>=1.3; extra == "sqlalchemy"
Provides-Extra: tests
Requires-Dist: requests_kerberos; extra == "tests"
Requires-Dist: sqlalchemy>=1.3; extra == "tests"
Requires-Dist: requests_gssapi; extra == "tests"
Requires-Dist: krb5==0.5.1; extra == "tests"
Requires-Dist: httpretty<1.1; extra == "tests"
Requires-Dist: pytest; extra == "tests"
Requires-Dist: pytest-runner; extra == "tests"
Requires-Dist: pre-commit; extra == "tests"
Requires-Dist: black; extra == "tests"
Requires-Dist: isort; extra == "tests"
Requires-Dist: keyring; extra == "tests"
Requires-Dist: testcontainers; extra == "tests"
Requires-Dist: boto3; extra == "tests"
Provides-Extra: external-authentication-token-cache
Requires-Dist: keyring; extra == "external-authentication-token-cache"
Dynamic: author
Dynamic: author-email
Dynamic: classifier
Dynamic: description
Dynamic: description-content-type
Dynamic: home-page
Dynamic: license
Dynamic: license-file
Dynamic: provides-extra
Dynamic: requires-dist
Dynamic: requires-python
Dynamic: summary
